<properties>

	<property id="ActivityColor" type="number">0xFFFFFF</property>
    <property id="BackgroundColor" type="number">0x000000</property>
    <property id="DateColor" type="number">0xAAAAAA</property>
    <property id="GraphicsColor" type="number">0xFFAA00</property>
    <property id="TimeColor" type="number">0xFFFFFF</property>
    <property id="UpperfieldColor" type="number">0xAAAAAA</property>
    
    <property id="Activity1" type="number">1</property>
    <property id="Activity2" type="number">2</property>
    
   
</properties>
